tablecache/__init__.py
tablecache/cache.py
tablecache/db.py
tablecache/index.py
tablecache/metrics.py
tablecache/storage.py
tablecache/types.py
tablecache/local/__init__.py
tablecache/local/storage.py
tablecache/postgres/__init__.py
tablecache/postgres/db.py
tablecache/redis/__init__.py
tablecache/redis/codec.py
tablecache/redis/storage.py
tablecache-4.3.0.dist-info/LICENSE
tablecache-4.3.0.dist-info/METADATA
tablecache-4.3.0.dist-info/WHEEL
tablecache-4.3.0.dist-info/top_level.txt
tablecache-4.3.0.dist-info/RECORD
