Metadata-Version: 2.1
Name: tablecache
Version: 4.3.0
Summary: Simple cache for unwieldily joined relations.
Author: Marc Lehmann
Author-email: marc.lehmann@gmx.de
License: AGPL-3.0-or-later
Project-URL: Github, https://github.com/dddsnn/tablecache
Project-URL: Documentation, https://tablecache.readthedocs.io
Requires-Python: >=3.12
License-File: LICENSE
Provides-Extra: dev
Requires-Dist: prometheus-client ==0.20.0 ; extra == 'dev'
Requires-Dist: autopep8 >=2.0.4 ; extra == 'dev'
Requires-Dist: sphinx-rtd-theme ==2.*,>=2.0.0 ; extra == 'dev'
Requires-Dist: aiorwlock ==1.4.0 ; extra == 'dev'
Requires-Dist: sphinx ==7.*,>=7.2.6 ; extra == 'dev'
Requires-Dist: pytest ==7.*,>=7.4.0 ; extra == 'dev'
Requires-Dist: PyHamcrest >=2.0.4 ; extra == 'dev'
Requires-Dist: myst-parser ==2.*,>=2.0.0 ; extra == 'dev'
Requires-Dist: asyncpg >=0.27.0 ; extra == 'dev'
Requires-Dist: pytest-asyncio ==0.21.1 ; extra == 'dev'
Requires-Dist: flake8 >=6.1.0 ; extra == 'dev'
Requires-Dist: Flake8-pyproject >=1.2.3 ; extra == 'dev'
Requires-Dist: sortedcontainers ==2.*,>=2.4.0 ; extra == 'dev'
Requires-Dist: redis[hiredis] ==4.*,>=4.5.5 ; extra == 'dev'
Provides-Extra: docs
Requires-Dist: sphinx-rtd-theme ==2.*,>=2.0.0 ; extra == 'docs'
Requires-Dist: myst-parser ==2.*,>=2.0.0 ; extra == 'docs'
Requires-Dist: sphinx ==7.*,>=7.2.6 ; extra == 'docs'
Provides-Extra: local
Requires-Dist: aiorwlock ==1.4.0 ; extra == 'local'
Requires-Dist: sortedcontainers ==2.*,>=2.4.0 ; extra == 'local'
Provides-Extra: postgres
Requires-Dist: asyncpg >=0.27.0 ; extra == 'postgres'
Provides-Extra: prometheus
Requires-Dist: prometheus-client ==0.20.0 ; extra == 'prometheus'
Provides-Extra: redis
Requires-Dist: redis[hiredis] ==4.*,>=4.5.5 ; extra == 'redis'
Requires-Dist: aiorwlock ==1.4.0 ; extra == 'redis'
Provides-Extra: test
Requires-Dist: prometheus-client ==0.20.0 ; extra == 'test'
Requires-Dist: aiorwlock ==1.4.0 ; extra == 'test'
Requires-Dist: pytest ==7.*,>=7.4.0 ; extra == 'test'
Requires-Dist: PyHamcrest >=2.0.4 ; extra == 'test'
Requires-Dist: asyncpg >=0.27.0 ; extra == 'test'
Requires-Dist: pytest-asyncio ==0.21.1 ; extra == 'test'
Requires-Dist: sortedcontainers ==2.*,>=2.4.0 ; extra == 'test'
Requires-Dist: redis[hiredis] ==4.*,>=4.5.5 ; extra == 'test'
